spotpython/budget/ocba.py
spotpython/build/__init__.py
spotpython/build/kriging.py
spotpython/build/surrogates.py
spotpython/data/base.py
spotpython/data/california.py
spotpython/data/california_housing.py
spotpython/data/csvdataset.py
spotpython/data/data.csv
spotpython/data/data.pkl
spotpython/data/diabetes.py
spotpython/data/friedman.py
spotpython/data/lightcrossvalidationdatamodule.py
spotpython/data/lightdatamodule.py
spotpython/data/manydataset.py
spotpython/data/mnistdatamodule.py
spotpython/data/pkldataset.py
spotpython/data/torchdata.py
spotpython/data/vbdp.py
spotpython/design/__init__.py
spotpython/design/clustered.py
spotpython/design/designs.py
spotpython/design/factorial.py
spotpython/design/grid.py
spotpython/design/poor.py
spotpython/design/random.py
spotpython/design/sobol.py
spotpython/design/spacefilling.py
spotpython/design/utils.py
spotpython/fun/__init__.py
spotpython/fun/hyperlight.py
spotpython/fun/hypersklearn.py
spotpython/fun/hypertorch.py
spotpython/fun/mohyperlight.py
spotpython/fun/multiobjectivefunctions.py
spotpython/fun/objectivefunctions.py
spotpython/fun/xai_hyperlight.py
spotpython/gp/covar.py
spotpython/gp/distances.py
spotpython/gp/functions.py
spotpython/gp/gp.py
spotpython/gp/gp_sep.py
spotpython/gp/likelihood.py
spotpython/gp/linalg.py
spotpython/gp/lite.py
spotpython/gp/matrix.py
spotpython/gp/regressor.py
spotpython/gp/util.py
spotpython/hyperdict/light_hyper_dict.json
spotpython/hyperdict/light_hyper_dict.py
spotpython/hyperdict/sklearn_hyper_dict.json
spotpython/hyperdict/sklearn_hyper_dict.py
spotpython/hyperdict/torch_hyper_dict.json
spotpython/hyperdict/torch_hyper_dict.py
spotpython/hyperparameters/architecture.py
spotpython/hyperparameters/categorical.py
spotpython/hyperparameters/listgenerator.py
spotpython/hyperparameters/optimizer.py
spotpython/hyperparameters/values.py
spotpython/light/cvmodel.py
spotpython/light/litmodel.py
spotpython/light/loadmodel.py
spotpython/light/predictmodel.py
spotpython-0.35.3.dist-info/licenses/LICENSE.txt
spotpython-0.35.3.dist-info/.DS_Store
spotpython-0.35.3.dist-info/METADATA
spotpython-0.35.3.dist-info/WHEEL
spotpython-0.35.3.dist-info/top_level.txt
spotpython-0.35.3.dist-info/RECORD
