Metadata-Version: 2.4
Name: spotpython
Version: 0.35.3
Summary: spotpython - Sequential Parameter Optimization in Python
Author-email: "T. Bartz-Beielstein" <tbb@bartzundbartz.de>
License-Expression: AGPL-3.0-or-later
Project-URL: Homepage, https://www.spotseven.de
Project-URL: Issues, https://github.com/sequential-parameter-optimization/spotpython/issues
Project-URL: Repository, https://github.com/sequential-parameter-optimization/spotpython
Classifier: Programming Language :: Python :: 3.10
Classifier: Programming Language :: Python :: 3.11
Classifier: Programming Language :: Python :: 3.12
Classifier: Programming Language :: Python :: 3.13
Classifier: Operating System :: OS Independent
Requires-Python: >=3.10
License-File: LICENSE.txt
Requires-Dist: build
Requires-Dist: captum
Requires-Dist: factor_analyzer
Requires-Dist: forestci
Requires-Dist: graphviz
Requires-Dist: lightning>=2.0.0rc0
Requires-Dist: mapie
Requires-Dist: matplotlib
Requires-Dist: mkdocs>=1.6.0
Requires-Dist: mkdocs-material>=9.5.33
Requires-Dist: mkdocstrings-python>=1.10.8
Requires-Dist: mkdocs-exclude>=1.0.2
Requires-Dist: mkdocs-gen-files>=0.5.0
Requires-Dist: mkdocs-literate-nav>=0.6.1
Requires-Dist: mkdocs-section-index>=0.3.9
Requires-Dist: numpy>=2.0.0
Requires-Dist: nbformat
Requires-Dist: pandas
Requires-Dist: plotly
Requires-Dist: pytest
Requires-Dist: pytest-mock
Requires-Dist: python-markdown-math
Requires-Dist: river>=0.22.0
Requires-Dist: scikit-learn
Requires-Dist: scipy
Requires-Dist: spotriver>=0.4.1
Requires-Dist: spotdesirability
Requires-Dist: seaborn
Requires-Dist: statsmodels
Requires-Dist: tabulate
Requires-Dist: tensorboard
Requires-Dist: torch
Requires-Dist: torchdiffeq
Requires-Dist: torch-tb-profiler
Requires-Dist: torchmetrics
Requires-Dist: torchvision
Requires-Dist: torchviz
Dynamic: license-file
